hack4u/__init__.py
hack4u/courses.py
hack4u/utils.py
Shack4u-0.5.0.dist-info/METADATA
Shack4u-0.5.0.dist-info/WHEEL
Shack4u-0.5.0.dist-info/top_level.txt
Shack4u-0.5.0.dist-info/RECORD
