Metadata-Version: 2.1
Name: Shack4u
Version: 0.5.0
Summary: Una biblioteca para consultar cursos de hack4u.
Home-page: https://Shack4u.io
Author: Saul Villarreal
